swissdutch/constants.py
swissdutch/dutch.py
swissdutch/pairing.py
swissdutch/player.py
swissdutch/swiss.py
swissdutch/__init__.py
swissdutch-0.1.0.dist-info/DESCRIPTION.rst
swissdutch-0.1.0.dist-info/METADATA
swissdutch-0.1.0.dist-info/metadata.json
swissdutch-0.1.0.dist-info/RECORD
swissdutch-0.1.0.dist-info/top_level.txt
swissdutch-0.1.0.dist-info/WHEEL
