Metadata-Version: 1.1
Name: swissdutch
Version: 0.1.0
Summary: An implementation of the Swiss Dutch pairing system in Python
Home-page: https://github.com/rmoritz/swissdutch
Author: Ralph Moritz
Author-email: ralphmoritz@outlook.com
License: MIT
Keywords: swiss,pairing,dutch,system,chess,tournament
Platform: UNKNOWN
Classifier: Development Status :: 3 - Alpha
Classifier: Intended Audience :: Developers
Classifier: License :: OSI Approved :: MIT License
Classifier: Topic :: Software Development :: Libraries :: Python Modules
Classifier: Operating System :: OS Independent
Classifier: Programming Language :: Python :: 3
Classifier: Programming Language :: Python :: 3.4
